mp_common_pkg/__init__.py
mp_common_pkg/common.py
mp_common_pkg/global_const.py
mp_common_pkg-0.0.5.dist-info/LICENSE.txt
mp_common_pkg-0.0.5.dist-info/METADATA
mp_common_pkg-0.0.5.dist-info/WHEEL
mp_common_pkg-0.0.5.dist-info/top_level.txt
mp_common_pkg-0.0.5.dist-info/RECORD
