Metadata-Version: 2.1
Name: mp-common-pkg
Version: 0.0.5
Summary: A common repository, for MP System
Home-page: https://github.com/aaronmack/MP-common
Author: Aaron Li
Author-email: lilong999000@gmail.com
License: MIT
Keywords: COMMON,FUNCTIONS
Platform: UNKNOWN
Classifier: Programming Language :: Python :: 3
Classifier: License :: OSI Approved :: MIT License
Classifier: Operating System :: OS Independent
Requires-Python: >=3.6
Requires-Dist: crypto
Requires-Dist: colorama
